classy_dataclasses/ClassyDataclass.py
classy_dataclasses/ClassyField.py
classy_dataclasses/__init__.py
classy_dataclasses-1.0.2.dist-info/LICENSE
classy_dataclasses-1.0.2.dist-info/METADATA
classy_dataclasses-1.0.2.dist-info/WHEEL
classy_dataclasses-1.0.2.dist-info/entry_points.txt
classy_dataclasses-1.0.2.dist-info/RECORD
